<Properties StartupConfiguration="{DF9B0BD9-8A89-48EB-B103-028B459F0393}|Default">
  <MonoDevelop.MonoDroid LastDeploySdkVersion="12.3.3.3" />
  <MonoDevelop.Ide.ItemProperties.BaseApp-Xamarin.iOS PreferredExecutionTarget="MonoDevelop.IPhone.IPhoneSimulatorTarget.E313495A-0194-48F0-A62C-10B0128D3AD1" />
  <MonoDevelop.Ide.Workbench ActiveDocument="azure-pipelines.yml">
    <Files>
      <File FileName="azure-pipelines.yml" Line="78" Column="37" />
    </Files>
    <Pads>
      <Pad Id="ProjectPad">
        <State name="__root__">
          <Node name="BaseApp-Xamarin" expanded="True" />
        </State>
      </Pad>
      <Pad Id="MonoDevelop.Debugger.WatchPad">
        <State />
      </Pad>
    </Pads>
  </MonoDevelop.Ide.Workbench>
  <MultiItemStartupConfigurations />
  <MonoDevelop.Ide.Workspace ActiveConfiguration="Debug" />
  <MonoDevelop.Ide.DebuggingService.PinnedWatches />
  <MonoDevelop.Ide.DebuggingService.Breakpoints>
    <BreakpointStore />
  </MonoDevelop.Ide.DebuggingService.Breakpoints>
  <MonoDevelop.Ide.ItemProperties.BaseApp-Xamarin.Android PreferredExecutionTarget="Android.pixel_5_-_api_30" />
  <Xamarin.Addins.Core.Project ActiveDebugTarget="Android.pixel_5_-_api_30" />
</Properties>